setux/actions/package.py
setux/actions/service.py
setux/core/__init__.py
setux/core/action.py
setux/core/distro.py
setux/core/errors.py
setux/core/logger.py
setux/core/manage.py
setux/core/mapping.py
setux/core/module.py
setux/core/package.py
setux/core/plugins.py
setux/core/service.py
setux/core/target.py
setux_core-0.2507.1.dist-info/METADATA
setux_core-0.2507.1.dist-info/WHEEL
setux_core-0.2507.1.dist-info/top_level.txt
setux_core-0.2507.1.dist-info/RECORD
